logml/__init__.py
logml/_version.py
logml/logger.py
logml/time_utils.py
loggerml-1.2.0.dist-info/LICENSE
loggerml-1.2.0.dist-info/METADATA
loggerml-1.2.0.dist-info/WHEEL
loggerml-1.2.0.dist-info/top_level.txt
loggerml-1.2.0.dist-info/RECORD
