Metadata-Version: 2.2
Name: loggerml
Version: 1.2.0
Summary: Log your ml training in the console in an attractive way.
Author-email: Valentin Goldite <valentin.goldite@gmail.com>
Project-URL: Source, https://github.com/valentingol/logml
Keywords: logging,machine,learning
Classifier: Programming Language :: Python :: 3
Requires-Python: >=3.7
License-File: LICENSE
Requires-Dist: rich
